totEnJ/Heisenberg_exchange_from_total_energy.py
totEnJ/__init__.py
totEnJ/prepare_spin_states.py
totEnJ/utils.py
totEnJ-0.1.2.dist-info/LICENSE
totEnJ-0.1.2.dist-info/METADATA
totEnJ-0.1.2.dist-info/WHEEL
totEnJ-0.1.2.dist-info/top_level.txt
totEnJ-0.1.2.dist-info/RECORD
