Metadata-Version: 2.1
Name: totEnJ
Version: 0.1.2
Summary: Heisenberg Hamitlonian parametrization from ab initio total energy of magnetic supercells
Author: L. Vojacek
Author-email: Libor.Vojacek@vutbr.cz
License: BSD 3-Clause License
License-File: LICENSE
Requires-Dist: numpy
Requires-Dist: matplotlib
Requires-Dist: sympy
Requires-Dist: ase
Requires-Dist: pytest
Requires-Dist: pytest-cov
Requires-Dist: pytest-mpl
